{  
   "units":[  
      {  
         "id":"317"
      },
      {  
         "id":"325"
      },
      {  
         "id":"343"
      },
      {  
         "id":"369"
      },
      {  
         "id":"375"
      },
      {  
         "id":"376"
      },
      {  
         "id":"402"
      },
      {  
         "id":"440"
      },
      {  
         "id":"446"
      },
      {  
         "id":"476"
      },
      {  
         "id":"487"
      },
      {  
         "id":"493"
      },
      {  
         "id":"499"
      },
      {  
         "id":"517"
      },
      {  
         "id":"529"
      },
      {  
         "id":"547"
      },
      {  
         "id":"549"
      },
      {  
         "id":"560"
      },
      {  
         "id":"578"
      },
      {  
         "id":"627"
      },
      {  
         "id":"676"
      },
      {  
         "id":"654"
      },
      {  
         "id":"672"
      },
      {  
         "id":"705"
      },
      {  
         "id":"714"
      },
      {  
         "id":"7059"
      },
      {  
         "id":"7037"
      },
      {  
         "id":"7080"
      },
      {  
         "id":"8002"
      }
   ]
}